setup.py
lightning/__init__.py
lightning/classes.py
lightning/describegraph_nov_21.json
lightning/utils.py
lightning_utils.egg-info/PKG-INFO
lightning_utils.egg-info/SOURCES.txt
lightning_utils.egg-info/dependency_links.txt
lightning_utils.egg-info/requires.txt
lightning_utils.egg-info/top_level.txt