Metadata-Version: 1.0
Name: lightning-utils
Version: 0.1
Summary: lightning analysis
Home-page: UNKNOWN
Author: saart
Author-email: saart@cs.huji.ac.il
License: UNKNOWN
Platform: UNKNOWN
